e621/__init__.py
e621/e621.py
e621-0.1.0.dist-info/LICENSE
e621-0.1.0.dist-info/METADATA
e621-0.1.0.dist-info/WHEEL
e621-0.1.0.dist-info/top_level.txt
e621-0.1.0.dist-info/RECORD
