Metadata-Version: 2.1
Name: e621
Version: 0.1.0
Summary: e621.net API wrapper written in Python
Home-page: https://github.com/PatriotRossii/e621-py
Author: PatriotRossii
Author-email: patriotrossii2019@mail.ru
License: UNKNOWN
Platform: UNKNOWN
Classifier: Programming Language :: Python :: 3
Classifier: License :: OSI Approved :: MIT License
Classifier: Operating System :: OS Independent
Requires-Python: >=3.6
